figurative/__init__.py
figurative/apps.py
figurative/blocks.py
figurative/static/figurative/css/figurative.css
figurative/static/figurative/js/figurative.js
figurative/templates/figurative/blocks/figure_block.html
figurative/templates/figurative/blocks/slideshow_block.html
figurative/templatetags/__init__.py
figurative/templatetags/figurative_tags.py
figurative-4.1.0.dist-info/AUTHORS.txt
figurative-4.1.0.dist-info/LICENSE.txt
figurative-4.1.0.dist-info/METADATA
figurative-4.1.0.dist-info/WHEEL
figurative-4.1.0.dist-info/top_level.txt
figurative-4.1.0.dist-info/RECORD
